ccl_scratch_tools/__init__.py
ccl_scratch_tools/blocks.py
ccl_scratch_tools/parse.py
ccl_scratch_tools/sb3_schema.py
ccl_scratch_tools/scrape.py
ccl_scratch_tools/visualize.py
ccl_scratch_tools/scratch_to_blocks/blocks.py
ccl_scratch_tools-0.1.6.dist-info/LICENSE
ccl_scratch_tools-0.1.6.dist-info/METADATA
ccl_scratch_tools-0.1.6.dist-info/WHEEL
ccl_scratch_tools-0.1.6.dist-info/top_level.txt
ccl_scratch_tools-0.1.6.dist-info/RECORD
