Metadata-Version: 2.1
Name: ccl-scratch-tools
Version: 0.1.6
Summary: Tools with which to work with Scratch JSON files.
Home-page: https://github.com/GSE-CCL/scratch-tools
Author: Creative Computing Lab
Author-email: jarchibald@college.harvard.edu
License: UNKNOWN
Project-URL: Documentation, https://ccl-scratch-tools.readthedocs.io/en/latest/
Platform: UNKNOWN
Classifier: Programming Language :: Python :: 3
Classifier: License :: OSI Approved :: MIT License
Classifier: Operating System :: OS Independent
Requires-Python: >=3.7
Requires-Dist: bs4
Requires-Dist: jsonschema
Requires-Dist: requests
